LICENSE
requirements.txt
dbgen/__init__.py
dbgen/__main__.py
dbgen/cli/__init__.py
dbgen/cli/etl_step.py
dbgen/cli/main.py
dbgen/cli/model.py
dbgen/cli/new.py
dbgen/cli/options.py
dbgen/cli/queries.py
dbgen/cli/run.py
dbgen/cli/styles.py
dbgen/cli/utils.py
dbgen/configuration.py
dbgen/core/__init__.py
dbgen/core/args.py
dbgen/core/attribute.py
dbgen/core/base.py
dbgen/core/context.py
dbgen/core/dashboard.py
dbgen/core/decorators.py
dbgen/core/dependency.py
dbgen/core/entity.py
dbgen/core/etl_step.py
dbgen/core/func.py
dbgen/core/generator.py
dbgen/core/metadata.py
dbgen/core/model.py
dbgen/core/node/__init__.py
dbgen/core/node/common_extractors.py
dbgen/core/node/computational_node.py
dbgen/core/node/extract.py
dbgen/core/node/load.py
dbgen/core/node/query.py
dbgen/core/node/transforms.py
dbgen/core/run.py
dbgen/core/statement_parsing.py
dbgen/core/type_registry.py
dbgen/exceptions.py
dbgen/providers/__init__.py
dbgen/providers/aws/__init__.py
dbgen/providers/aws/extract.py
dbgen/templates/__init__.py
dbgen/templates/insert.sql.jinja
dbgen/templates/update.sql.jinja
dbgen/types.py
dbgen/utils/__init__.py
dbgen/utils/graphs.py
dbgen/utils/lists.py
dbgen/utils/log.py
dbgen/utils/misc.py
dbgen/utils/sql.py
dbgen/utils/type_coercion.py
dbgen/utils/typing.py
modelyst_dbgen-0.6.1.dist-info/entry_points.txt
modelyst_dbgen-0.6.1.dist-info/LICENSE
modelyst_dbgen-0.6.1.dist-info/WHEEL
modelyst_dbgen-0.6.1.dist-info/METADATA
modelyst_dbgen-0.6.1.dist-info/RECORD
