Metadata-Version: 2.1
Name: modelyst-dbgen
Version: 0.6.1
Summary: DBgen (Database Generator) is an open-source Python library for connecting raw data, scientific theories, and relational databases
Home-page: https://www.dbgen.modelyst.com
License: Apache-2.0
Keywords: ETL,Postgres,Databases
Author: Michael Statt
Author-email: michael.statt@modelyst.io
Maintainer: Michael Statt
Maintainer-email: michael.statt@modelyst.io
Requires-Python: >=3.8,<4.0
Classifier: Environment :: Console
Classifier: Intended Audience :: Developers
Classifier: Intended Audience :: Science/Research
Classifier: License :: OSI Approved :: Apache Software License
Classifier: Programming Language :: Python :: 3
Classifier: Programming Language :: Python :: 3.10
Classifier: Programming Language :: Python :: 3.8
Classifier: Programming Language :: Python :: 3.9
Provides-Extra: boto3
Requires-Dist: Jinja2 (>=3.0.1,<4.0.0)
Requires-Dist: SQLAlchemy (>=1.4.25,<2.0.0)
Requires-Dist: boto3 (>=1.21.0,<2.0.0); extra == "boto3"
Requires-Dist: cookiecutter (>=1.7.3,<2.0.0)
Requires-Dist: modelyst-sqlmodel (>=0.0.7,<0.0.8)
Requires-Dist: networkx (>=2.6.3,<3.0.0)
Requires-Dist: psutil (>=5.9.0,<6.0.0)
Requires-Dist: psycopg (>=3.0.1,<4.0.0)
Requires-Dist: psycopg2-binary (>=2.9.1,<3.0.0)
Requires-Dist: pydantic[dotenv] (>=1.8.2,<2.0.0)
Requires-Dist: pydasher (>=0.0.13,<0.0.14)
Requires-Dist: rich (>=11.1.0,<12.0.0)
Requires-Dist: typer (>=0.4.0,<0.5.0)
Requires-Dist: typing-extensions (>=3.10.0.1)
Project-URL: Documentation, https://www.dbgen.modelyst.com
Project-URL: Repository, https://github.com/modelyst/dbgen
